gen_wrapper/__init__.py
gen_wrapper/llm_cli.py
gen_wrapper/llm_client_factory.py
gen_wrapper/llm_wrapper.py
gen_wrapper/providers_config.py
gen_wrapper/llm_clients/__init__.py
gen_wrapper/llm_clients/anthropic_client.py
gen_wrapper/llm_clients/azure_openai_client.py
gen_wrapper/llm_clients/base.py
gen_wrapper/llm_clients/deepseek_client.py
gen_wrapper/llm_clients/fireworks_client.py
gen_wrapper/llm_clients/gemini_client.py
gen_wrapper/llm_clients/groq_client.py
gen_wrapper/llm_clients/llama_qwen_client.py
gen_wrapper/llm_clients/openai_client.py
gen_wrapper-0.1.1.dist-info/METADATA
gen_wrapper-0.1.1.dist-info/WHEEL
gen_wrapper-0.1.1.dist-info/entry_points.txt
gen_wrapper-0.1.1.dist-info/licenses/LICENSE
gen_wrapper-0.1.1.dist-info/RECORD
